antporter/__init__.py
antporter/cli.py
antporter/merger.py
antporter/metadata.py
antporter/splitter.py
antporter/utils.py
antporter-1.0.2.dist-info/licenses/LICENSE
antporter-1.0.2.dist-info/METADATA
antporter-1.0.2.dist-info/WHEEL
antporter-1.0.2.dist-info/entry_points.txt
antporter-1.0.2.dist-info/top_level.txt
antporter-1.0.2.dist-info/RECORD
