Metadata-Version: 2.4
Name: antporter
Version: 1.0.2
Summary: A simple tool for splitting and merging files to bypass HPC cluster file upload size limits
Author: AntPorter Team
License: MIT
Project-URL: Homepage, https://github.com/givemeone1astkiss/antporter
Project-URL: Repository, https://github.com/givemeone1astkiss/antporter
Keywords: file-split,file-merge,hpc,chunk,transfer
Classifier: Development Status :: 4 - Beta
Classifier: Intended Audience :: Developers
Classifier: Intended Audience :: Science/Research
Classifier: License :: OSI Approved :: MIT License
Classifier: Programming Language :: Python :: 3
Classifier: Programming Language :: Python :: 3.8
Classifier: Programming Language :: Python :: 3.9
Classifier: Programming Language :: Python :: 3.10
Classifier: Programming Language :: Python :: 3.11
Classifier: Programming Language :: Python :: 3.12
Classifier: Topic :: System :: Archiving
Classifier: Topic :: Utilities
Requires-Python: >=3.8
License-File: LICENSE
Requires-Dist: tqdm>=4.65.0
Provides-Extra: dev
Requires-Dist: pytest>=7.0.0; extra == "dev"
Requires-Dist: black>=23.0.0; extra == "dev"
Requires-Dist: flake8>=6.0.0; extra == "dev"
Dynamic: license-file
